.gitignore
.travis.yml
CHANGES.txt
MANIFEST.in
README.rst
development.ini
setup.cfg
setup.py
kotti_calendar/__init__.py
kotti_calendar/fanstatic.py
kotti_calendar/resources.py
kotti_calendar/views.py
kotti_calendar/widgets.py
kotti_calendar.egg-info/PKG-INFO
kotti_calendar.egg-info/SOURCES.txt
kotti_calendar.egg-info/dependency_links.txt
kotti_calendar.egg-info/entry_points.txt
kotti_calendar.egg-info/not-zip-safe
kotti_calendar.egg-info/requires.txt
kotti_calendar.egg-info/top_level.txt
kotti_calendar/alembic/script.py.mako
kotti_calendar/alembic/versions/1617f961c382_subclass_event_from_.py
kotti_calendar/alembic/versions/1c3e72660e31_subclass_calendar_fr.py
kotti_calendar/alembic/versions/4b26aa5e798e_add_link_to_file.py
kotti_calendar/locale/kotti_calendar.pot
kotti_calendar/locale/de/LC_MESSAGES/kotti_calendar.mo
kotti_calendar/locale/de/LC_MESSAGES/kotti_calendar.po
kotti_calendar/static/style.css
kotti_calendar/static/style.min.css
kotti_calendar/templates/calendar-view.pt
kotti_calendar/templates/event-view.pt
kotti_calendar/templates/upcoming-events.pt
kotti_calendar/tests/browser.txt
kotti_calendar/tests/conftest.py
kotti_calendar/tests/test_widgets.py