Metadata-Version: 1.1
Name: kotti-calendar
Version: 0.8.2
Summary: Add a calendar to your Kotti site
Home-page: http://pypi.python.org/pypi/kotti_calendar
Author: Daniel Nouri
Author-email: daniel.nouri@gmail.com
License: BSD-derived (http://www.repoze.org/LICENSE.txt)
Keywords: calendar fullcalendar kotti cms pylons pyramid
Platform: UNKNOWN
Classifier: Programming Language :: Python
Classifier: Framework :: Pylons
Classifier: Topic :: Internet :: WWW/HTTP
Classifier: Topic :: Internet :: WWW/HTTP :: Dynamic Content
Classifier: Topic :: Internet :: WWW/HTTP :: WSGI :: Application
Classifier: License :: Repoze Public License
